odoo/addons/l10n_it_website_portal_fiscalcode/README.rst
odoo/addons/l10n_it_website_portal_fiscalcode/__init__.py
odoo/addons/l10n_it_website_portal_fiscalcode/__manifest__.py
odoo/addons/l10n_it_website_portal_fiscalcode/controllers/__init__.py
odoo/addons/l10n_it_website_portal_fiscalcode/controllers/main.py
odoo/addons/l10n_it_website_portal_fiscalcode/i18n/it.po
odoo/addons/l10n_it_website_portal_fiscalcode/i18n/l10n_it_website_portal_fiscalcode.pot
odoo/addons/l10n_it_website_portal_fiscalcode/readme/CONTRIBUTORS.md
odoo/addons/l10n_it_website_portal_fiscalcode/readme/DESCRIPTION.md
odoo/addons/l10n_it_website_portal_fiscalcode/static/description/icon.png
odoo/addons/l10n_it_website_portal_fiscalcode/static/description/index.html
odoo/addons/l10n_it_website_portal_fiscalcode/tests/__init__.py
odoo/addons/l10n_it_website_portal_fiscalcode/tests/test_my_account.py
odoo/addons/l10n_it_website_portal_fiscalcode/views/l10n_it_website_portal_fiscalcode_templates.xml
odoo_addon_l10n_it_website_portal_fiscalcode-18.0.1.0.0.2.dist-info/METADATA
odoo_addon_l10n_it_website_portal_fiscalcode-18.0.1.0.0.2.dist-info/WHEEL
odoo_addon_l10n_it_website_portal_fiscalcode-18.0.1.0.0.2.dist-info/top_level.txt
odoo_addon_l10n_it_website_portal_fiscalcode-18.0.1.0.0.2.dist-info/RECORD
