Metadata-Version: 2.1
Name: odoo-addon-l10n_it_website_portal_fiscalcode
Version: 18.0.1.0.0.2
Requires-Python: >=3.10
Requires-Dist: odoo-addon-l10n_it_edi_extension==18.0.*
Requires-Dist: odoo==18.0.*
Summary: Add fiscal code to details of frontend user
Home-page: https://github.com/OCA/l10n-italy
License: AGPL-3
Author: Odoo Community Association (OCA)
Author-email: support@odoo-community.org
Classifier: Programming Language :: Python
Classifier: Framework :: Odoo
Classifier: Framework :: Odoo :: 18.0
Classifier: License :: OSI Approved :: GNU Affero General Public License v3
